plicense
tests
