Metadata-Version: 1.0
Name: plicense
Version: 0.2.1
Summary: Make sure all source files have your standard licensing stub at the top.
Home-page: https://github.com/dsoprea/LicensePrepend
Author: Dustin Oprea
Author-email: myselfasunder@gmail.com
License: GPL 2
Keywords: license
Platform: UNKNOWN
